bin/__init__.py
bin/common/AppConfigurations.py
bin/common/AppConstants.py
bin/common/__init__.py
bin/core/__init__.py
bin/core/applications/Annotations.py
bin/core/applications/AuditManagement.py
bin/core/applications/AuditManagementModules.py
bin/core/applications/AuditUserManagementStrategies.py
bin/core/applications/__init__.py
bin/core/persistences/PersistenceAdaptor.py
bin/core/persistences/__init__.py
bin/core/persistences/adaptors/CassandraPersistenceAdaptor.py
bin/core/persistences/adaptors/__init__.py
bin/core/services/__init__.py
bin/core/services/audit_service.py
bin/util/CommonUtils.py
bin/util/LoggerUtil.py
bin/util/Logging.py
bin/util/__init__.py
conf/__init__.py
logs/__init__.py
upload/__init__.py
upload/__root__.py
new_framework-0.1.dist-info/METADATA
new_framework-0.1.dist-info/WHEEL
new_framework-0.1.dist-info/top_level.txt
new_framework-0.1.dist-info/RECORD
